{"_env":"NODEJS","_serializationMethod":"normal","_autosave":false,"_autosaveInterval":5000,"_collections":[{"name":"items","unindexedSortComparator":"js","defaultLokiOperatorPackage":"js","_dynamicViews":[],"uniqueNames":[],"transforms":{},"rangedIndexes":{},"_data":[{"slug":"git1","title":"여러개의 GIT 계정 사용하기","toc":[{"id":"개요","depth":2,"text":"개요"},{"id":"1-ssh-key-생성","depth":2,"text":"1. SSH key 생성"},{"id":"2-git-계정-설정파일","depth":2,"text":"2. GIT 계정 설정파일"},{"id":"3-git-서버와-통신","depth":2,"text":"3. GIT 서버와 통신"},{"id":"ssh-agent로-key-저장","depth":2,"text":"SSH Agent로 key 저장"},{"id":"폴더별-git-계정-연동","depth":2,"text":"폴더별 GIT 계정 연동"}],"body":{"type":"root","children":[{"type":"element","tag":"h1","props":{"id":"여러개의-git-계정-사용하기"},"children":[{"type":"element","tag":"a","props":{"ariaHidden":"true","href":"#%EC%97%AC%EB%9F%AC%EA%B0%9C%EC%9D%98-git-%EA%B3%84%EC%A0%95-%EC%82%AC%EC%9A%A9%ED%95%98%EA%B8%B0","tabIndex":-1},"children":[{"type":"element","tag":"span","props":{"className":["icon","icon-link"]},"children":[]}]},{"type":"text","value":"여러개의 GIT 계정 사용하기"}]},{"type":"text","value":"\n"},{"type":"element","tag":"h2","props":{"id":"개요"},"children":[{"type":"element","tag":"a","props":{"ariaHidden":"true","href":"#%EA%B0%9C%EC%9A%94","tabIndex":-1},"children":[{"type":"element","tag":"span","props":{"className":["icon","icon-link"]},"children":[]}]},{"type":"text","value":"개요"}]},{"type":"text","value":"\n"},{"type":"element","tag":"p","props":{},"children":[{"type":"text","value":"하나의 컴퓨터에서 여러개의 GIT 계정을 사용해서 작업하고자 하는 경우 이 내용을 적용하면 된다. 보통 GIT 계정은 자격증명관리자에 저장되어서 사용되는데 1개의 계정만 사용가능하다. 이때 SSH를 사용해서 GIT 서버와 통신하면 여러개의 GIT 계정을 사용할 수 있다."}]},{"type":"text","value":"\n"},{"type":"element","tag":"h2","props":{"id":"1-ssh-key-생성"},"children":[{"type":"element","tag":"a","props":{"ariaHidden":"true","href":"#1-ssh-key-%EC%83%9D%EC%84%B1","tabIndex":-1},"children":[{"type":"element","tag":"span","props":{"className":["icon","icon-link"]},"children":[]}]},{"type":"text","value":"1. SSH key 생성"}]},{"type":"text","value":"\n"},{"type":"element","tag":"p","props":{},"children":[{"type":"text","value":"SSH를 사용하는 경우 GIT 서버와 비대칭키 방식으로 통신하므로 GIT 서버는 SSH 공개키가 필요하다. SSH 키를 저장할 .ssh라는 디렉토리를 홈디렉토리안에 만들고 ssh-keygen이라는 프로그램으로 각 계정별로 공개키와 개인키를 생성한다. 이후 GITHUB에서 Settings > SSH and GPG keys > SSH keys에 들어가서 앞서 만든 공개키를 등록한다."}]},{"type":"text","value":"\n"},{"type":"element","tag":"div","props":{"className":["nuxt-content-highlight"]},"children":[{"type":"element","tag":"pre","props":{"className":["language-bash","line-numbers"]},"children":[{"type":"element","tag":"code","props":{},"children":[{"type":"text","value":"    "},{"type":"element","tag":"span","props":{"className":["token","comment"]},"children":[{"type":"text","value":"# 개인 계정"}]},{"type":"text","value":"\n    ssh-keygen -t rsa -C "},{"type":"element","tag":"span","props":{"className":["token","punctuation"]},"children":[{"type":"text","value":"{"}]},{"type":"text","value":"personal "},{"type":"element","tag":"span","props":{"className":["token","function"]},"children":[{"type":"text","value":"git"}]},{"type":"text","value":" email"},{"type":"element","tag":"span","props":{"className":["token","punctuation"]},"children":[{"type":"text","value":"}"}]},{"type":"text","value":"\n    "},{"type":"element","tag":"span","props":{"className":["token","comment"]},"children":[{"type":"text","value":"# 회사 계정"}]},{"type":"text","value":"\n    ssh-keygen -t rsa -C "},{"type":"element","tag":"span","props":{"className":["token","punctuation"]},"children":[{"type":"text","value":"{"}]},{"type":"text","value":"company "},{"type":"element","tag":"span","props":{"className":["token","function"]},"children":[{"type":"text","value":"git"}]},{"type":"text","value":" email"},{"type":"element","tag":"span","props":{"className":["token","punctuation"]},"children":[{"type":"text","value":"}"}]},{"type":"text","value":"\n"}]}]}]},{"type":"text","value":"\n"},{"type":"element","tag":"h2","props":{"id":"2-git-계정-설정파일"},"children":[{"type":"element","tag":"a","props":{"ariaHidden":"true","href":"#2-git-%EA%B3%84%EC%A0%95-%EC%84%A4%EC%A0%95%ED%8C%8C%EC%9D%BC","tabIndex":-1},"children":[{"type":"element","tag":"span","props":{"className":["icon","icon-link"]},"children":[]}]},{"type":"text","value":"2. GIT 계정 설정파일"}]},{"type":"text","value":"\n"},{"type":"element","tag":"p","props":{},"children":[{"type":"text","value":".ssh 폴더 안에 config라는 파일을 만들고 계정별로 사용할 개인키를 지정해준다."}]},{"type":"text","value":"\n"},{"type":"element","tag":"div","props":{"className":["nuxt-content-highlight"]},"children":[{"type":"element","tag":"pre","props":{"className":["language-bash","line-numbers"]},"children":[{"type":"element","tag":"code","props":{},"children":[{"type":"text","value":"    "},{"type":"element","tag":"span","props":{"className":["token","comment"]},"children":[{"type":"text","value":"# 개인 계정"}]},{"type":"text","value":"\n    Host "},{"type":"element","tag":"span","props":{"className":["token","punctuation"]},"children":[{"type":"text","value":"{"}]},{"type":"text","value":"personal "},{"type":"element","tag":"span","props":{"className":["token","function"]},"children":[{"type":"text","value":"git"}]},{"type":"text","value":" "},{"type":"element","tag":"span","props":{"className":["token","function"]},"children":[{"type":"text","value":"host"}]},{"type":"text","value":" name"},{"type":"element","tag":"span","props":{"className":["token","punctuation"]},"children":[{"type":"text","value":"}"}]},{"type":"text","value":"\n    HostName github.com\n    User "},{"type":"element","tag":"span","props":{"className":["token","function"]},"children":[{"type":"text","value":"git"}]},{"type":"text","value":"\n    IdentityFile ~/.ssh/"},{"type":"element","tag":"span","props":{"className":["token","punctuation"]},"children":[{"type":"text","value":"{"}]},{"type":"text","value":"personal "},{"type":"element","tag":"span","props":{"className":["token","function"]},"children":[{"type":"text","value":"git"}]},{"type":"text","value":" private key name"},{"type":"element","tag":"span","props":{"className":["token","punctuation"]},"children":[{"type":"text","value":"}"}]},{"type":"text","value":"\n        \n    "},{"type":"element","tag":"span","props":{"className":["token","comment"]},"children":[{"type":"text","value":"# 회사 계정"}]},{"type":"text","value":"\n    Host "},{"type":"element","tag":"span","props":{"className":["token","punctuation"]},"children":[{"type":"text","value":"{"}]},{"type":"text","value":"company "},{"type":"element","tag":"span","props":{"className":["token","function"]},"children":[{"type":"text","value":"git"}]},{"type":"text","value":" "},{"type":"element","tag":"span","props":{"className":["token","function"]},"children":[{"type":"text","value":"host"}]},{"type":"text","value":" name"},{"type":"element","tag":"span","props":{"className":["token","punctuation"]},"children":[{"type":"text","value":"}"}]},{"type":"text","value":" \n    HostName github.com\n    User "},{"type":"element","tag":"span","props":{"className":["token","function"]},"children":[{"type":"text","value":"git"}]},{"type":"text","value":"\n    IdentityFile ~/.ssh/"},{"type":"element","tag":"span","props":{"className":["token","punctuation"]},"children":[{"type":"text","value":"{"}]},{"type":"text","value":"company "},{"type":"element","tag":"span","props":{"className":["token","function"]},"children":[{"type":"text","value":"git"}]},{"type":"text","value":" private key name"},{"type":"element","tag":"span","props":{"className":["token","punctuation"]},"children":[{"type":"text","value":"}"}]},{"type":"text","value":"\n"}]}]}]},{"type":"text","value":"\n"},{"type":"element","tag":"h2","props":{"id":"3-git-서버와-통신"},"children":[{"type":"element","tag":"a","props":{"ariaHidden":"true","href":"#3-git-%EC%84%9C%EB%B2%84%EC%99%80-%ED%86%B5%EC%8B%A0","tabIndex":-1},"children":[{"type":"element","tag":"span","props":{"className":["icon","icon-link"]},"children":[]}]},{"type":"text","value":"3. GIT 서버와 통신"}]},{"type":"text","value":"\n"},{"type":"element","tag":"div","props":{"className":["nuxt-content-highlight"]},"children":[{"type":"element","tag":"pre","props":{"className":["language-bash","line-numbers"]},"children":[{"type":"element","tag":"code","props":{},"children":[{"type":"text","value":"    "},{"type":"element","tag":"span","props":{"className":["token","comment"]},"children":[{"type":"text","value":"# git 서버와 SSH 통신 테스트"}]},{"type":"text","value":"\n    "},{"type":"element","tag":"span","props":{"className":["token","function"]},"children":[{"type":"text","value":"ssh"}]},{"type":"text","value":" -T "},{"type":"element","tag":"span","props":{"className":["token","punctuation"]},"children":[{"type":"text","value":"{"}]},{"type":"text","value":"git "},{"type":"element","tag":"span","props":{"className":["token","function"]},"children":[{"type":"text","value":"host"}]},{"type":"text","value":" name"},{"type":"element","tag":"span","props":{"className":["token","punctuation"]},"children":[{"type":"text","value":"}"}]},{"type":"text","value":"\n\n    "},{"type":"element","tag":"span","props":{"className":["token","comment"]},"children":[{"type":"text","value":"# git remote repository 등록"}]},{"type":"text","value":"\n    "},{"type":"element","tag":"span","props":{"className":["token","function"]},"children":[{"type":"text","value":"git"}]},{"type":"text","value":" remote "},{"type":"element","tag":"span","props":{"className":["token","function"]},"children":[{"type":"text","value":"add"}]},{"type":"text","value":" origin git@"},{"type":"element","tag":"span","props":{"className":["token","punctuation"]},"children":[{"type":"text","value":"{"}]},{"type":"text","value":"git "},{"type":"element","tag":"span","props":{"className":["token","function"]},"children":[{"type":"text","value":"host"}]},{"type":"text","value":" name"},{"type":"element","tag":"span","props":{"className":["token","punctuation"]},"children":[{"type":"text","value":"}"}]},{"type":"text","value":":"},{"type":"element","tag":"span","props":{"className":["token","punctuation"]},"children":[{"type":"text","value":"{"}]},{"type":"text","value":"git repository name"},{"type":"element","tag":"span","props":{"className":["token","punctuation"]},"children":[{"type":"text","value":"}"}]},{"type":"text","value":"\n"}]}]}]},{"type":"text","value":"\n"},{"type":"element","tag":"h2","props":{"id":"ssh-agent로-key-저장"},"children":[{"type":"element","tag":"a","props":{"ariaHidden":"true","href":"#ssh-agent%EB%A1%9C-key-%EC%A0%80%EC%9E%A5","tabIndex":-1},"children":[{"type":"element","tag":"span","props":{"className":["icon","icon-link"]},"children":[]}]},{"type":"text","value":"SSH Agent로 key 저장"}]},{"type":"text","value":"\n"},{"type":"element","tag":"p","props":{},"children":[{"type":"text","value":"GIT 서버에 요청을 보낼때마다 key 생성시 입력한 비밀번호를 입력해야 하는데 SSH Agent를 사용해서 비밀번호를 저장하면 매번 입력할 필요없다."}]},{"type":"text","value":"\n"},{"type":"element","tag":"div","props":{"className":["nuxt-content-highlight"]},"children":[{"type":"element","tag":"pre","props":{"className":["language-bash","line-numbers"]},"children":[{"type":"element","tag":"code","props":{},"children":[{"type":"text","value":"    "},{"type":"element","tag":"span","props":{"className":["token","comment"]},"children":[{"type":"text","value":"# ssh-agent 실행"}]},{"type":"text","value":"\n    "},{"type":"element","tag":"span","props":{"className":["token","builtin","class-name"]},"children":[{"type":"text","value":"eval"}]},{"type":"text","value":" "},{"type":"element","tag":"span","props":{"className":["token","string"]},"children":[{"type":"text","value":"\""},{"type":"element","tag":"span","props":{"className":["token","variable"]},"children":[{"type":"element","tag":"span","props":{"className":["token","variable"]},"children":[{"type":"text","value":"$("}]},{"type":"text","value":"ssh-agent -s"},{"type":"element","tag":"span","props":{"className":["token","variable"]},"children":[{"type":"text","value":")"}]}]},{"type":"text","value":"\""}]},{"type":"text","value":"\n    "},{"type":"element","tag":"span","props":{"className":["token","comment"]},"children":[{"type":"text","value":"# ssh key 조회"}]},{"type":"text","value":"\n    ssh-add -l\n    "},{"type":"element","tag":"span","props":{"className":["token","comment"]},"children":[{"type":"text","value":"# ssh key 저장"}]},{"type":"text","value":"\n    ssh-add ~/.ssh/"},{"type":"element","tag":"span","props":{"className":["token","punctuation"]},"children":[{"type":"text","value":"{"}]},{"type":"text","value":"git private key"},{"type":"element","tag":"span","props":{"className":["token","punctuation"]},"children":[{"type":"text","value":"}"}]},{"type":"text","value":"\n"}]}]}]},{"type":"text","value":"\n"},{"type":"element","tag":"h2","props":{"id":"폴더별-git-계정-연동"},"children":[{"type":"element","tag":"a","props":{"ariaHidden":"true","href":"#%ED%8F%B4%EB%8D%94%EB%B3%84-git-%EA%B3%84%EC%A0%95-%EC%97%B0%EB%8F%99","tabIndex":-1},"children":[{"type":"element","tag":"span","props":{"className":["icon","icon-link"]},"children":[]}]},{"type":"text","value":"폴더별 GIT 계정 연동"}]},{"type":"text","value":"\n"},{"type":"element","tag":"p","props":{},"children":[{"type":"text","value":"앞에서 GIT 계정별로 GIT 서버와 통신하는 경우를 봤다면 로컬에서 작업할때 폴더별로 GIT 계정을 연동할 수 있다. home 디렉토리의 .gitconfig 파일을 수정해준다."}]},{"type":"text","value":"\n"},{"type":"element","tag":"div","props":{"className":["nuxt-content-highlight"]},"children":[{"type":"element","tag":"pre","props":{"className":["language-bash","line-numbers"]},"children":[{"type":"element","tag":"code","props":{},"children":[{"type":"text","value":"    "},{"type":"element","tag":"span","props":{"className":["token","comment"]},"children":[{"type":"text","value":"# .gitconfig 파일"}]},{"type":"text","value":"\n    "},{"type":"element","tag":"span","props":{"className":["token","punctuation"]},"children":[{"type":"text","value":"["}]},{"type":"text","value":"user"},{"type":"element","tag":"span","props":{"className":["token","punctuation"]},"children":[{"type":"text","value":"]"}]},{"type":"text","value":"\n        email "},{"type":"element","tag":"span","props":{"className":["token","operator"]},"children":[{"type":"text","value":"="}]},{"type":"text","value":" "},{"type":"element","tag":"span","props":{"className":["token","punctuation"]},"children":[{"type":"text","value":"{"}]},{"type":"text","value":"personal "},{"type":"element","tag":"span","props":{"className":["token","function"]},"children":[{"type":"text","value":"git"}]},{"type":"text","value":" email"},{"type":"element","tag":"span","props":{"className":["token","punctuation"]},"children":[{"type":"text","value":"}"}]},{"type":"text","value":"\n        name "},{"type":"element","tag":"span","props":{"className":["token","operator"]},"children":[{"type":"text","value":"="}]},{"type":"text","value":" "},{"type":"element","tag":"span","props":{"className":["token","punctuation"]},"children":[{"type":"text","value":"{"}]},{"type":"text","value":"personal "},{"type":"element","tag":"span","props":{"className":["token","function"]},"children":[{"type":"text","value":"git"}]},{"type":"text","value":" username"},{"type":"element","tag":"span","props":{"className":["token","punctuation"]},"children":[{"type":"text","value":"}"}]},{"type":"text","value":"\n    "},{"type":"element","tag":"span","props":{"className":["token","punctuation"]},"children":[{"type":"text","value":"["}]},{"type":"text","value":"includeIf "},{"type":"element","tag":"span","props":{"className":["token","string"]},"children":[{"type":"text","value":"\"gitdir:{company 작업 폴더 경로}\""}]},{"type":"element","tag":"span","props":{"className":["token","punctuation"]},"children":[{"type":"text","value":"]"}]},{"type":"text","value":"\n    path "},{"type":"element","tag":"span","props":{"className":["token","operator"]},"children":[{"type":"text","value":"="}]},{"type":"text","value":" .gitconfig-comapny\n\n    "},{"type":"element","tag":"span","props":{"className":["token","comment"]},"children":[{"type":"text","value":"# .gitconfig-company 파일"}]},{"type":"text","value":"\n    "},{"type":"element","tag":"span","props":{"className":["token","punctuation"]},"children":[{"type":"text","value":"["}]},{"type":"text","value":"user"},{"type":"element","tag":"span","props":{"className":["token","punctuation"]},"children":[{"type":"text","value":"]"}]},{"type":"text","value":"\n        email "},{"type":"element","tag":"span","props":{"className":["token","operator"]},"children":[{"type":"text","value":"="}]},{"type":"text","value":" "},{"type":"element","tag":"span","props":{"className":["token","punctuation"]},"children":[{"type":"text","value":"{"}]},{"type":"text","value":"company "},{"type":"element","tag":"span","props":{"className":["token","function"]},"children":[{"type":"text","value":"git"}]},{"type":"text","value":" email"},{"type":"element","tag":"span","props":{"className":["token","punctuation"]},"children":[{"type":"text","value":"}"}]},{"type":"text","value":"\n        name "},{"type":"element","tag":"span","props":{"className":["token","operator"]},"children":[{"type":"text","value":"="}]},{"type":"text","value":" "},{"type":"element","tag":"span","props":{"className":["token","punctuation"]},"children":[{"type":"text","value":"{"}]},{"type":"text","value":"company "},{"type":"element","tag":"span","props":{"className":["token","function"]},"children":[{"type":"text","value":"git"}]},{"type":"text","value":" username"},{"type":"element","tag":"span","props":{"className":["token","punctuation"]},"children":[{"type":"text","value":"}"}]},{"type":"text","value":"\n"}]}]}]}]},"text":"\n# 여러개의 GIT 계정 사용하기\n\n## 개요\n하나의 컴퓨터에서 여러개의 GIT 계정을 사용해서 작업하고자 하는 경우 이 내용을 적용하면 된다. 보통 GIT 계정은 자격증명관리자에 저장되어서 사용되는데 1개의 계정만 사용가능하다. 이때 SSH를 사용해서 GIT 서버와 통신하면 여러개의 GIT 계정을 사용할 수 있다.\n\n## 1. SSH key 생성\nSSH를 사용하는 경우 GIT 서버와 비대칭키 방식으로 통신하므로 GIT 서버는 SSH 공개키가 필요하다. SSH 키를 저장할 .ssh라는 디렉토리를 홈디렉토리안에 만들고 ssh-keygen이라는 프로그램으로 각 계정별로 공개키와 개인키를 생성한다. 이후 GITHUB에서 Settings > SSH and GPG keys > SSH keys에 들어가서 앞서 만든 공개키를 등록한다.\n\n``` bash\n    # 개인 계정\n    ssh-keygen -t rsa -C {personal git email}\n    # 회사 계정\n    ssh-keygen -t rsa -C {company git email}\n```\n\n## 2. GIT 계정 설정파일\n.ssh 폴더 안에 config라는 파일을 만들고 계정별로 사용할 개인키를 지정해준다.\n\n``` bash\n    # 개인 계정\n    Host {personal git host name}\n    HostName github.com\n    User git\n    IdentityFile ~/.ssh/{personal git private key name}\n        \n    # 회사 계정\n    Host {company git host name} \n    HostName github.com\n    User git\n    IdentityFile ~/.ssh/{company git private key name}\n```\n\n## 3. GIT 서버와 통신\n``` bash\n    # git 서버와 SSH 통신 테스트\n    ssh -T {git host name}\n\n    # git remote repository 등록\n    git remote add origin git@{git host name}:{git repository name}\n```\n\n## SSH Agent로 key 저장\nGIT 서버에 요청을 보낼때마다 key 생성시 입력한 비밀번호를 입력해야 하는데 SSH Agent를 사용해서 비밀번호를 저장하면 매번 입력할 필요없다.\n\n``` bash\n    # ssh-agent 실행\n    eval \"$(ssh-agent -s)\"\n    # ssh key 조회\n    ssh-add -l\n    # ssh key 저장\n    ssh-add ~/.ssh/{git private key}\n```\n\n## 폴더별 GIT 계정 연동\n앞에서 GIT 계정별로 GIT 서버와 통신하는 경우를 봤다면 로컬에서 작업할때 폴더별로 GIT 계정을 연동할 수 있다. home 디렉토리의 .gitconfig 파일을 수정해준다. \n\n``` bash\n    # .gitconfig 파일\n    [user]\n        email = {personal git email}\n        name = {personal git username}\n    [includeIf \"gitdir:{company 작업 폴더 경로}\"]\n    path = .gitconfig-comapny\n\n    # .gitconfig-company 파일\n    [user]\n        email = {company git email}\n        name = {company git username}\n```\n\n\n\n\n\n\n\n","dir":"/git/core","path":"/git/core/git1","extension":".md","createdAt":"2022-05-06T07:13:04.471Z","updatedAt":"2022-05-06T07:13:04.471Z","meta":{"version":0,"revision":0,"created":1651821273361},"$loki":1},{"slug":"test1","description":"test content 1","title":"test content 1","toc":[],"body":{"type":"root","children":[{"type":"element","tag":"p","props":{},"children":[{"type":"text","value":"spring core test content 1"}]}]},"text":"spring core test content 1\n","dir":"/spring/core","path":"/spring/core/test1","extension":".md","createdAt":"2022-05-06T07:13:04.471Z","updatedAt":"2022-05-06T07:13:04.471Z","meta":{"version":0,"revision":0,"created":1651821273364},"$loki":2},{"slug":"test1","description":"test content 1","title":"test content 1","toc":[],"body":{"type":"root","children":[{"type":"element","tag":"p","props":{},"children":[{"type":"text","value":"spring jpa test content 1"}]}]},"text":"spring jpa test content 1\n","dir":"/spring/jpa","path":"/spring/jpa/test1","extension":".md","createdAt":"2022-05-06T07:13:04.471Z","updatedAt":"2022-05-06T07:13:04.471Z","meta":{"version":0,"revision":0,"created":1651821273365},"$loki":3},{"slug":"test1","description":"test content 1","title":"test content 1","toc":[],"body":{"type":"root","children":[{"type":"element","tag":"p","props":{},"children":[{"type":"text","value":"vue core test content 1"}]}]},"text":"vue core test content 1\n","dir":"/vue/core","path":"/vue/core/test1","extension":".md","createdAt":"2022-05-06T07:13:04.471Z","updatedAt":"2022-05-06T07:13:04.471Z","meta":{"version":0,"revision":0,"created":1651821273367},"$loki":4}],"idIndex":[1,2,3,4],"maxId":4,"_dirty":true,"_nestedProperties":[],"transactional":false,"asyncListeners":false,"disableMeta":false,"disableChangesApi":true,"disableDeltaChangesApi":true,"cloneObjects":false,"cloneMethod":"deep","changes":[],"_fullTextSearch":{"ii":{"title":{"_store":true,"_optimizeChanges":true,"docCount":4,"docStore":[[0,{"fieldLength":4}],[1,{"fieldLength":3}],[2,{"fieldLength":3}],[3,{"fieldLength":3}]],"totalFieldLength":13,"root":{"k":[50668,103,44228,49324,116,99,49],"v":[{"k":[47084],"v":[{"k":[44060],"v":[{"k":[51032],"v":[{"d":{"df":1,"dc":[[0,1]]}}]}]}]},{"k":[105],"v":[{"k":[116],"v":[{"d":{"df":1,"dc":[[0,1]]}}]}]},{"k":[51221],"v":[{"d":{"df":1,"dc":[[0,1]]}}]},{"k":[50857],"v":[{"k":[54616],"v":[{"k":[44592],"v":[{"d":{"df":1,"dc":[[0,1]]}}]}]}]},{"k":[101],"v":[{"k":[115],"v":[{"k":[116],"v":[{"d":{"df":3,"dc":[[1,1],[2,1],[3,1]]}}]}]}]},{"k":[111],"v":[{"k":[110],"v":[{"k":[116],"v":[{"k":[101],"v":[{"k":[110],"v":[{"k":[116],"v":[{"d":{"df":3,"dc":[[1,1],[2,1],[3,1]]}}]}]}]}]}]}]},{"d":{"df":3,"dc":[[1,1],[2,1],[3,1]]}}]}},"description":{"_store":true,"_optimizeChanges":true,"docCount":3,"docStore":[[1,{"fieldLength":3}],[2,{"fieldLength":3}],[3,{"fieldLength":3}]],"totalFieldLength":9,"root":{"k":[116,99,49],"v":[{"k":[101],"v":[{"k":[115],"v":[{"k":[116],"v":[{"d":{"df":3,"dc":[[1,1],[2,1],[3,1]]}}]}]}]},{"k":[111],"v":[{"k":[110],"v":[{"k":[116],"v":[{"k":[101],"v":[{"k":[110],"v":[{"k":[116],"v":[{"d":{"df":3,"dc":[[1,1],[2,1],[3,1]]}}]}]}]}]}]}]},{"d":{"df":3,"dc":[[1,1],[2,1],[3,1]]}}]}},"slug":{"_store":true,"_optimizeChanges":true,"docCount":4,"docStore":[[0,{"fieldLength":1}],[1,{"fieldLength":1}],[2,{"fieldLength":1}],[3,{"fieldLength":1}]],"totalFieldLength":4,"root":{"k":[103,116],"v":[{"k":[105],"v":[{"k":[116],"v":[{"k":[49],"v":[{"d":{"df":1,"dc":[[0,1]]}}]}]}]},{"k":[101],"v":[{"k":[115],"v":[{"k":[116],"v":[{"k":[49],"v":[{"d":{"df":3,"dc":[[1,1],[2,1],[3,1]]}}]}]}]}]}]}},"text":{"_store":true,"_optimizeChanges":true,"docCount":4,"docStore":[[0,{"fieldLength":310}],[1,{"fieldLength":5}],[2,{"fieldLength":5}],[3,{"fieldLength":5}]],"totalFieldLength":325,"root":{"k":[35,50668,103,44228,49324,44060,54616,52980,51089,44221,51060,45236,51201,46108,48372,51088,51200,49,115,49436,53685,49688,51080,107,49373,48708,48169,44277,54596,53412,46,46356,54856,47564,54532,44033,62,97,46308,50526,46321,96,98,45,114,123,101,54924,50,49444,54260,50504,99,54028,51648,104,110,117,105,126,112,51,53580,111,50836,51077,47588,49892,34,51312,50672,48420,47196,91,61,116,106,118],"v":[{"d":{"df":1,"dc":[[0,12]]},"k":[35],"v":[{"d":{"df":1,"dc":[[0,6]]}}]},{"k":[47084],"v":[{"k":[44060],"v":[{"k":[51032],"v":[{"d":{"df":1,"dc":[[0,3]]}}]}]}]},{"k":[105,112],"v":[{"k":[116],"v":[{"d":{"df":1,"dc":[[0,29]]},"k":[104,64],"v":[{"k":[117],"v":[{"k":[98],"v":[{"k":[50640,46],"v":[{"k":[49436],"v":[{"d":{"df":1,"dc":[[0,1]]}}]},{"k":[99],"v":[{"k":[111],"v":[{"k":[109],"v":[{"d":{"df":1,"dc":[[0,2]]}}]}]}]}]}]}]},{"k":[123],"v":[{"k":[103],"v":[{"k":[105],"v":[{"k":[116],"v":[{"d":{"df":1,"dc":[[0,1]]}}]}]}]}]}]}]},{"k":[103],"v":[{"d":{"df":1,"dc":[[0,1]]}}]}]},{"k":[51221],"v":[{"d":{"df":1,"dc":[[0,7]]},"k":[51012,51008,47564,48324],"v":[{"d":{"df":1,"dc":[[0,3]]}},{"d":{"df":1,"dc":[[0,1]]}},{"d":{"df":1,"dc":[[0,1]]}},{"k":[47196],"v":[{"d":{"df":1,"dc":[[0,3]]}}]}]}]},{"k":[50857],"v":[{"k":[54616,54644,46104,44032,54624],"v":[{"k":[44592,45716],"v":[{"d":{"df":1,"dc":[[0,1]]}},{"d":{"df":1,"dc":[[0,1]]}}]},{"k":[49436],"v":[{"d":{"df":1,"dc":[[0,3]]}}]},{"k":[45716],"v":[{"k":[45936],"v":[{"d":{"df":1,"dc":[[0,1]]}}]}]},{"k":[45733],"v":[{"k":[54616],"v":[{"k":[45796],"v":[{"k":[46],"v":[{"d":{"df":1,"dc":[[0,1]]}}]}]}]}]},{"d":{"df":1,"dc":[[0,2]]}}]}]},{"k":[50836,51064],"v":[{"d":{"df":1,"dc":[[0,1]]}},{"d":{"df":1,"dc":[[0,2]]},"k":[53412],"v":[{"k":[47484],"v":[{"d":{"df":1,"dc":[[0,2]]}}]}]}]},{"k":[45208,45716],"v":[{"k":[51032],"v":[{"d":{"df":1,"dc":[[0,1]]}}]},{"d":{"df":1,"dc":[[0,1]]},"k":[45936],"v":[{"d":{"df":1,"dc":[[0,1]]}}]}]},{"k":[54504],"v":[{"k":[53552],"v":[{"k":[50640],"v":[{"k":[49436],"v":[{"d":{"df":1,"dc":[[0,1]]}}]}]}]}]},{"k":[50629],"v":[{"d":{"df":1,"dc":[[0,1]]},"k":[54616,54624],"v":[{"k":[44256],"v":[{"k":[51088],"v":[{"d":{"df":1,"dc":[[0,1]]}}]}]},{"k":[46412],"v":[{"d":{"df":1,"dc":[[0,1]]}}]}]}]},{"k":[50864,47196],"v":[{"d":{"df":1,"dc":[[0,2]]},"k":[47484],"v":[{"d":{"df":1,"dc":[[0,1]]}}]},{"k":[125],"v":[{"k":[34],"v":[{"k":[93],"v":[{"d":{"df":1,"dc":[[0,1]]}}]}]}]}]},{"d":{"df":1,"dc":[[0,1]]},"k":[46412,54980],"v":[{"d":{"df":1,"dc":[[0,1]]}},{"d":{"df":1,"dc":[[0,1]]}}]},{"k":[50857],"v":[{"k":[51012],"v":[{"d":{"df":1,"dc":[[0,1]]}}]}]},{"k":[50857],"v":[{"k":[54616],"v":[{"k":[47732],"v":[{"d":{"df":1,"dc":[[0,1]]}}]}]}]},{"k":[45796],"v":[{"k":[46],"v":[{"d":{"df":1,"dc":[[0,1]]}}]}]},{"k":[53685,45244],"v":[{"d":{"df":1,"dc":[[0,1]]}},{"k":[46412],"v":[{"k":[47560],"v":[{"k":[45796],"v":[{"d":{"df":1,"dc":[[0,1]]}}]}]}]}]},{"k":[44201],"v":[{"k":[51613],"v":[{"k":[47749],"v":[{"k":[44288],"v":[{"k":[47532],"v":[{"k":[51088],"v":[{"k":[50640],"v":[{"d":{"df":1,"dc":[[0,1]]}}]}]}]}]}]}]}]},{"k":[51109],"v":[{"d":{"df":1,"dc":[[0,2]]},"k":[46104,54624,54616],"v":[{"k":[50612],"v":[{"k":[49436],"v":[{"d":{"df":1,"dc":[[0,1]]}}]}]},{"d":{"df":1,"dc":[[0,1]]}},{"k":[47732],"v":[{"d":{"df":1,"dc":[[0,1]]}}]}]}]},{"d":{"df":3,"dc":[[1,1],[2,1],[3,1]]},"k":[44060,46],"v":[{"k":[51032],"v":[{"d":{"df":1,"dc":[[0,1]]}}]},{"d":{"df":1,"dc":[[0,1]]}}]},{"k":[115,101,112],"v":[{"k":[104],"v":[{"d":{"df":1,"dc":[[0,11]]},"k":[47484,45],"v":[{"d":{"df":1,"dc":[[0,2]]}},{"k":[107,97],"v":[{"k":[101],"v":[{"k":[121],"v":[{"k":[103],"v":[{"k":[101],"v":[{"k":[110],"v":[{"d":{"df":1,"dc":[[0,2]]},"k":[51060],"v":[{"k":[46972],"v":[{"k":[45716],"v":[{"d":{"df":1,"dc":[[0,1]]}}]}]}]}]}]}]}]}]},{"k":[103,100],"v":[{"k":[101],"v":[{"k":[110],"v":[{"k":[116],"v":[{"d":{"df":1,"dc":[[0,1]]}}]}]}]},{"k":[100],"v":[{"d":{"df":1,"dc":[[0,2]]}}]}]}]}]}]},{"k":[116],"v":[{"k":[116],"v":[{"k":[105],"v":[{"k":[110],"v":[{"k":[103],"v":[{"k":[115],"v":[{"d":{"df":1,"dc":[[0,1]]}}]}]}]}]}]}]},{"k":[114],"v":[{"k":[105],"v":[{"k":[110],"v":[{"k":[103],"v":[{"d":{"df":2,"dc":[[1,1],[2,1]]}}]}]}]}]}]},{"k":[48260],"v":[{"k":[50752,45716,50640],"v":[{"d":{"df":1,"dc":[[0,5]]}},{"d":{"df":1,"dc":[[0,1]]}},{"d":{"df":1,"dc":[[0,1]]}}]}]},{"k":[49888],"v":[{"d":{"df":1,"dc":[[0,2]]},"k":[54616],"v":[{"k":[47732,48064,45716],"v":[{"d":{"df":1,"dc":[[0,1]]}},{"k":[47196],"v":[{"d":{"df":1,"dc":[[0,1]]}}]},{"d":{"df":1,"dc":[[0,1]]}}]}]}]},{"d":{"df":1,"dc":[[0,2]]},"k":[51221],"v":[{"k":[54644],"v":[{"k":[51456],"v":[{"k":[45796],"v":[{"k":[46],"v":[{"d":{"df":1,"dc":[[0,1]]}}]}]}]}]}]},{"k":[45796],"v":[{"k":[46],"v":[{"d":{"df":1,"dc":[[0,2]]}}]}]},{"k":[101],"v":[{"k":[121],"v":[{"d":{"df":1,"dc":[[0,7]]},"k":[115,125],"v":[{"d":{"df":1,"dc":[[0,1]]},"k":[50640],"v":[{"d":{"df":1,"dc":[[0,1]]}}]},{"d":{"df":1,"dc":[[0,1]]}}]}]}]},{"k":[49457],"v":[{"d":{"df":1,"dc":[[0,1]]},"k":[54620,49884],"v":[{"k":[45796],"v":[{"k":[46],"v":[{"d":{"df":1,"dc":[[0,1]]}}]}]},{"d":{"df":1,"dc":[[0,1]]}}]}]},{"k":[45824,48128],"v":[{"k":[52845],"v":[{"k":[53412],"v":[{"d":{"df":1,"dc":[[0,1]]}}]}]},{"k":[48264],"v":[{"k":[54840],"v":[{"k":[47484],"v":[{"d":{"df":1,"dc":[[0,2]]}}]}]}]}]},{"k":[49885],"v":[{"k":[51004],"v":[{"k":[47196],"v":[{"d":{"df":1,"dc":[[0,1]]}}]}]}]},{"k":[44060],"v":[{"k":[53412],"v":[{"k":[44032,50752,47484],"v":[{"d":{"df":1,"dc":[[0,1]]}},{"d":{"df":1,"dc":[[0,1]]}},{"d":{"df":1,"dc":[[0,1]]}}]}]}]},{"k":[50836],"v":[{"k":[54616,50630],"v":[{"k":[45796],"v":[{"k":[46],"v":[{"d":{"df":1,"dc":[[0,1]]}}]}]},{"k":[45796],"v":[{"k":[46],"v":[{"d":{"df":1,"dc":[[0,1]]}}]}]}]}]},{"k":[47484],"v":[{"d":{"df":1,"dc":[[0,1]]}}]},{"k":[115,103],"v":[{"k":[115],"v":[{"k":[104],"v":[{"d":{"df":1,"dc":[[0,1]]},"k":[46972],"v":[{"k":[45716],"v":[{"d":{"df":1,"dc":[[0,1]]}}]}]}]}]},{"k":[105],"v":[{"k":[116],"v":[{"k":[99],"v":[{"k":[111],"v":[{"k":[110],"v":[{"k":[102],"v":[{"k":[105],"v":[{"k":[103],"v":[{"d":{"df":1,"dc":[[0,2]]},"k":[45],"v":[{"k":[99],"v":[{"k":[111],"v":[{"k":[109],"v":[{"k":[97,112],"v":[{"k":[112],"v":[{"k":[110],"v":[{"k":[121],"v":[{"d":{"df":1,"dc":[[0,1]]}}]}]}]},{"k":[97],"v":[{"k":[110],"v":[{"k":[121],"v":[{"d":{"df":1,"dc":[[0,1]]}}]}]}]}]}]}]}]}]}]}]}]}]}]}]}]}]}]},{"k":[47113],"v":[{"k":[53664],"v":[{"k":[47532],"v":[{"k":[47484,51032],"v":[{"d":{"df":1,"dc":[[0,1]]}},{"d":{"df":1,"dc":[[0,1]]}}]}]}]}]},{"k":[46356],"v":[{"k":[47113],"v":[{"k":[53664],"v":[{"k":[47532],"v":[{"k":[50504],"v":[{"k":[50640],"v":[{"d":{"df":1,"dc":[[0,1]]}}]}]}]}]}]}]},{"k":[46308,46304],"v":[{"k":[44256],"v":[{"d":{"df":1,"dc":[[0,2]]}}]},{"d":{"df":1,"dc":[[0,1]]}}]},{"k":[47196],"v":[{"k":[44536],"v":[{"k":[47016],"v":[{"k":[51004],"v":[{"k":[47196],"v":[{"d":{"df":1,"dc":[[0,1]]}}]}]}]}]}]},{"d":{"df":1,"dc":[[0,1]]}},{"d":{"df":1,"dc":[[0,2]]}},{"k":[110,100,103],"v":[{"k":[100],"v":[{"d":{"df":1,"dc":[[0,1]]}}]},{"k":[100],"v":[{"d":{"df":1,"dc":[[0,1]]}}]},{"k":[101],"v":[{"k":[110],"v":[{"k":[116],"v":[{"k":[47196,47484],"v":[{"d":{"df":1,"dc":[[0,1]]}},{"d":{"df":1,"dc":[[0,1]]}}]}]}]}]}]},{"k":[50612],"v":[{"k":[44032],"v":[{"k":[49436],"v":[{"d":{"df":1,"dc":[[0,1]]}}]}]}]},{"k":[49436,50640],"v":[{"d":{"df":1,"dc":[[0,1]]}},{"k":[49436],"v":[{"d":{"df":1,"dc":[[0,1]]}}]}]},{"k":[47197],"v":[{"d":{"df":1,"dc":[[0,1]]},"k":[54620],"v":[{"k":[45796],"v":[{"k":[46],"v":[{"d":{"df":1,"dc":[[0,1]]}}]}]}]}]},{"k":[96],"v":[{"k":[96],"v":[{"d":{"df":1,"dc":[[0,10]]}}]}]},{"k":[97],"v":[{"k":[115],"v":[{"k":[104],"v":[{"d":{"df":1,"dc":[[0,5]]}}]}]}]},{"k":[116,99,115,108],"v":[{"d":{"df":1,"dc":[[0,3]]}},{"d":{"df":1,"dc":[[0,2]]}},{"k":[41],"v":[{"k":[34],"v":[{"d":{"df":1,"dc":[[0,1]]}}]}]},{"d":{"df":1,"dc":[[0,1]]}}]},{"k":[115,101],"v":[{"k":[97],"v":[{"d":{"df":1,"dc":[[0,2]]}}]},{"k":[109,112],"v":[{"k":[111],"v":[{"k":[116],"v":[{"k":[101],"v":[{"d":{"df":1,"dc":[[0,2]]}}]}]}]},{"k":[111],"v":[{"k":[115],"v":[{"k":[105],"v":[{"k":[116],"v":[{"k":[111],"v":[{"k":[114],"v":[{"k":[121],"v":[{"d":{"df":1,"dc":[[0,2]]}}]}]}]}]}]}]}]}]}]},{"k":[112,99,103],"v":[{"k":[101],"v":[{"k":[114],"v":[{"k":[115],"v":[{"k":[111],"v":[{"k":[110],"v":[{"k":[97],"v":[{"k":[108],"v":[{"d":{"df":1,"dc":[[0,4]]}}]}]}]}]}]}]}]},{"k":[111],"v":[{"k":[109],"v":[{"k":[112],"v":[{"k":[97],"v":[{"k":[110],"v":[{"k":[121],"v":[{"d":{"df":1,"dc":[[0,4]]}}]}]}]}]}]}]},{"k":[105],"v":[{"k":[116],"v":[{"d":{"df":1,"dc":[[0,1]]}}]}]}]},{"k":[109,118],"v":[{"k":[97],"v":[{"k":[105],"v":[{"k":[108],"v":[{"d":{"df":1,"dc":[[0,2]]},"k":[125],"v":[{"d":{"df":1,"dc":[[0,4]]}}]}]}]}]},{"k":[97],"v":[{"k":[108],"v":[{"d":{"df":1,"dc":[[0,1]]}}]}]}]},{"k":[49324],"v":[{"d":{"df":1,"dc":[[0,2]]}}]},{"k":[46],"v":[{"d":{"df":1,"dc":[[0,1]]}}]},{"k":[51221],"v":[{"k":[54028],"v":[{"k":[51068],"v":[{"d":{"df":1,"dc":[[0,1]]}}]}]}]},{"k":[45908],"v":[{"d":{"df":1,"dc":[[0,2]]},"k":[48324],"v":[{"d":{"df":1,"dc":[[0,1]]},"k":[47196],"v":[{"d":{"df":1,"dc":[[0,1]]}}]}]}]},{"k":[50640],"v":[{"d":{"df":1,"dc":[[0,1]]}}]},{"k":[111],"v":[{"k":[110,114],"v":[{"k":[102,116],"v":[{"k":[105],"v":[{"k":[103],"v":[{"k":[46972],"v":[{"k":[45716],"v":[{"d":{"df":1,"dc":[[0,1]]}}]}]}]}]},{"k":[101],"v":[{"k":[110],"v":[{"k":[116],"v":[{"d":{"df":3,"dc":[[1,1],[2,1],[3,1]]}}]}]}]}]},{"k":[101],"v":[{"d":{"df":2,"dc":[[1,1],[3,1]]}}]}]}]},{"k":[51068],"v":[{"d":{"df":1,"dc":[[0,2]]},"k":[51012],"v":[{"d":{"df":1,"dc":[[0,2]]}}]}]},{"k":[51221],"v":[{"k":[54644],"v":[{"k":[51456],"v":[{"k":[45796],"v":[{"k":[46],"v":[{"d":{"df":1,"dc":[[0,1]]}}]}]}]}]}]},{"k":[111],"v":[{"k":[115,109],"v":[{"k":[116],"v":[{"d":{"df":1,"dc":[[0,6]]},"k":[110],"v":[{"k":[97],"v":[{"k":[109],"v":[{"k":[101],"v":[{"d":{"df":1,"dc":[[0,2]]}}]}]}]}]}]},{"k":[101],"v":[{"d":{"df":1,"dc":[[0,1]]}}]}]}]},{"k":[97],"v":[{"k":[109],"v":[{"k":[101],"v":[{"d":{"df":1,"dc":[[0,2]]},"k":[125],"v":[{"d":{"df":1,"dc":[[0,6]]},"k":[58],"v":[{"k":[123],"v":[{"k":[103],"v":[{"k":[105],"v":[{"k":[116],"v":[{"d":{"df":1,"dc":[[0,1]]}}]}]}]}]}]}]}]}]}]},{"k":[115],"v":[{"k":[101],"v":[{"k":[114],"v":[{"d":{"df":1,"dc":[[0,2]]},"k":[110],"v":[{"k":[97],"v":[{"k":[109],"v":[{"k":[101],"v":[{"k":[125],"v":[{"d":{"df":1,"dc":[[0,2]]}}]}]}]}]}]}]}]}]},{"k":[100],"v":[{"k":[101],"v":[{"k":[110],"v":[{"k":[116],"v":[{"k":[105],"v":[{"k":[116],"v":[{"k":[121],"v":[{"k":[102],"v":[{"k":[105],"v":[{"k":[108],"v":[{"k":[101],"v":[{"d":{"df":1,"dc":[[0,2]]}}]}]}]}]}]}]}]}]}]}]}]},{"k":[47],"v":[{"k":[46],"v":[{"k":[115],"v":[{"k":[115],"v":[{"k":[104],"v":[{"k":[47],"v":[{"k":[123],"v":[{"k":[112,99,103],"v":[{"k":[101],"v":[{"k":[114],"v":[{"k":[115],"v":[{"k":[111],"v":[{"k":[110],"v":[{"k":[97],"v":[{"k":[108],"v":[{"d":{"df":1,"dc":[[0,1]]}}]}]}]}]}]}]}]},{"k":[111],"v":[{"k":[109],"v":[{"k":[112],"v":[{"k":[97],"v":[{"k":[110],"v":[{"k":[121],"v":[{"d":{"df":1,"dc":[[0,1]]}}]}]}]}]}]}]},{"k":[105],"v":[{"k":[116],"v":[{"d":{"df":1,"dc":[[0,1]]}}]}]}]}]}]}]}]}]}]}]},{"k":[114,97],"v":[{"k":[105],"v":[{"k":[118],"v":[{"k":[97],"v":[{"k":[116],"v":[{"k":[101],"v":[{"d":{"df":1,"dc":[[0,3]]}}]}]}]}]}]},{"k":[116],"v":[{"k":[104],"v":[{"d":{"df":1,"dc":[[0,1]]}}]}]}]},{"k":[46],"v":[{"d":{"df":1,"dc":[[0,1]]}}]},{"k":[49828],"v":[{"k":[53944],"v":[{"d":{"df":1,"dc":[[0,1]]}}]}]},{"k":[114],"v":[{"k":[105],"v":[{"k":[103],"v":[{"k":[105],"v":[{"k":[110],"v":[{"d":{"df":1,"dc":[[0,1]]}}]}]}]}]}]},{"k":[52397],"v":[{"k":[51012],"v":[{"d":{"df":1,"dc":[[0,1]]}}]}]},{"k":[47141],"v":[{"k":[54620,54644,54624],"v":[{"d":{"df":1,"dc":[[0,1]]}},{"k":[50556],"v":[{"d":{"df":1,"dc":[[0,1]]}}]},{"d":{"df":1,"dc":[[0,1]]}}]}]},{"k":[48264],"v":[{"d":{"df":1,"dc":[[0,1]]}}]},{"k":[54665],"v":[{"d":{"df":1,"dc":[[0,1]]}}]},{"k":[36,103],"v":[{"k":[40],"v":[{"k":[115],"v":[{"k":[115],"v":[{"k":[104],"v":[{"k":[45],"v":[{"k":[97],"v":[{"k":[103],"v":[{"k":[101],"v":[{"k":[110],"v":[{"k":[116],"v":[{"d":{"df":1,"dc":[[0,1]]}}]}]}]}]}]}]}]}]}]}]},{"k":[105],"v":[{"k":[116],"v":[{"k":[100],"v":[{"k":[105],"v":[{"k":[114],"v":[{"k":[58],"v":[{"k":[123],"v":[{"k":[99],"v":[{"k":[111],"v":[{"k":[109],"v":[{"k":[112],"v":[{"k":[97],"v":[{"k":[110],"v":[{"k":[121],"v":[{"d":{"df":1,"dc":[[0,1]]}}]}]}]}]}]}]}]}]}]}]}]}]}]}]}]},{"k":[54924],"v":[{"d":{"df":1,"dc":[[0,1]]}}]},{"k":[46041],"v":[{"d":{"df":1,"dc":[[0,1]]},"k":[54624],"v":[{"d":{"df":1,"dc":[[0,1]]}}]}]},{"k":[45796],"v":[{"k":[47732],"v":[{"d":{"df":1,"dc":[[0,1]]}}]}]},{"k":[52972],"v":[{"k":[50640],"v":[{"k":[49436],"v":[{"d":{"df":1,"dc":[[0,1]]}}]}]}]},{"k":[117,105],"v":[{"k":[115],"v":[{"k":[101],"v":[{"k":[114],"v":[{"k":[93],"v":[{"d":{"df":1,"dc":[[0,2]]}}]}]}]}]},{"k":[110],"v":[{"k":[99],"v":[{"k":[108],"v":[{"k":[117],"v":[{"k":[100],"v":[{"k":[101],"v":[{"k":[105],"v":[{"k":[102],"v":[{"d":{"df":1,"dc":[[0,1]]}}]}]}]}]}]}]}]}]}]},{"d":{"df":1,"dc":[[0,5]]}},{"k":[101],"v":[{"k":[115],"v":[{"k":[116],"v":[{"d":{"df":3,"dc":[[1,1],[2,1],[3,1]]}}]}]}]},{"k":[112],"v":[{"k":[97],"v":[{"d":{"df":1,"dc":[[2,1]]}}]}]},{"k":[117],"v":[{"k":[101],"v":[{"d":{"df":1,"dc":[[3,1]]}}]}]}]}}}}}],"databaseVersion":1.5,"engineVersion":1.5,"filename":"content.db","_persistenceAdapter":null,"_persistenceMethod":null,"_throttledSaves":true}